{
  "type": "minecraft:chest",
  "pools": [
    {
      "bonus_rolls": 0.0,
      "rolls": 1.0,
      "entries": [

        {
          "type": "minecraft:item",
          "name": "minecraft:turtle_egg",
          "functions": [
            {
              "function": "set_components",
              "components": {"minecraft:item_name":{"translate":"精灵球","italic": false,"color": "aqua"},"minecraft:lore":[{"translate":"丢出后抓捕碰到的实体","italic": false,"color": "white"},{"translate":"再次丢出释放抓捕的实体","italic": false,"color": "white"},{"translate":"-使抓捕的实体失去【唤灵】标签","italic": false,"color": "gray"},{"translate":"*这可不是宝可梦决斗","italic": false,"color": "gray"}],"attribute_modifiers": [{"id": "no_put","type": "block_interaction_range","amount": -10,"operation": "add_value","slot": "hand"}],"tooltip_display": {"hidden_components": ["attribute_modifiers"]},"custom_data": {"pokemon_ball":1,"wallwar_item":1},"max_stack_size": 64}
            },
            {
              "function": "minecraft:set_count",
              "count": { "type": "minecraft:uniform", "min": 14, "max": 14 }
            }
          ]
        }
        ]
    },{
      "bonus_rolls": 0.0,
      "rolls": 1.0,
      "entries": [
        {
          "type": "minecraft:item",
          "name": "minecraft:sniffer_egg",
          "functions": [
            {
              "function": "set_components",
              "components": {"minecraft:item_name":{"translate":"大师球","italic": false,"color": "light_purple"},"minecraft:lore":[{"translate":"丢出后抓捕碰到的实体","italic": false,"color": "white"},{"translate":"再次丢出释放抓捕的实体并获得召回","italic": false,"color": "white"},{"translate":"手持丢出可以立即召回实体并治疗部分生命值","italic": false,"color": "white"},{"translate":"-使抓捕的实体持续时间改为300s（若有）","italic": false,"color": "gray"},{"translate":"*这就是宝可梦决斗","italic": false,"color": "gray"}],"attribute_modifiers": [{"id": "no_put","type": "block_interaction_range","amount": -10,"operation": "add_value","slot": "hand"}],"custom_data": {"pokemon_ball":1,"pokemon_master":1,"wallwar_item":1},"tooltip_display": {"hidden_components": ["attribute_modifiers"]},"max_stack_size": 1}
            },
            {
              "function": "minecraft:set_count",
              "count": 2
            }
          ]
        }
        ]
    },{
      "bonus_rolls": 0.0,
      "rolls": 1.0,
      "entries": [
        {
          "type": "minecraft:item",
          "name": "minecraft:zombie_spawn_egg",
          "functions": [
            {
              "function": "set_components",
              "components": {"minecraft:item_name":{"translate":"唤灵-小僵尸","italic": false,"color": "aqua"},"minecraft:lore":[{"translate":"丢出可以将其与自己绑定","italic": false,"color": "white"},{"translate":"召唤一个更加强大的僵尸","italic": false,"color": "red"},{"translate":"----------------------------","italic": false,"color": "gray"},{"translate":"生命值：","italic": false,"color": "gray"},{"translate":"持续时间：","italic": false,"color": "gray"},{"translate":"武器：","italic": false,"color": "gray"}],"entity_data": {"id": "zombie","PersistenceRequired": true,"IsBaby": true,"Health": 40,"CustomNameVisible": true,"CustomName": {"translate":"唤灵-小僵尸"},"equipment": {"head": {"id":"diamond_helmet","count": 1,"components": {"enchantments": {"protection": 4}}},"chest": {"id":"diamond_chestplate","count": 1,"components": {"enchantments": {"protection": 4}}},"legs": {"id":"diamond_leggings","count": 1,"components": {"enchantments": {"protection": 4}}},"feet": {"id":"diamond_boots","count": 1,"components": {"enchantments": {"protection": 4}}},"mainhand": {"id": "diamond_axe","count": 1,"components": {"enchantments": {"noench_pro3": 5}}}},"CanPickUpLoot": true,"drop_chances": {"head": 0,"chest": 0,"legs": 0,"feet": 0,"mainhand": 0,"offhand": 0},"attributes": [{"id": "max_health","base": 40},{"id": "follow_range","base": 64},{"id": "movement_speed","base": 0.28}]},"custom_data": {"spawn_egg":1,"wallwar_item":1},"max_stack_size": 16}
            }
          ]
        }
        ]
    },{
      "bonus_rolls": 0.0,
      "rolls": 1.0,
      "entries": [
        {
          "type": "minecraft:item",
          "name": "minecraft:skeleton_spawn_egg",
          "functions": [
            {
              "function": "set_components",
              "components": {"minecraft:item_name":{"translate":"唤灵-精英骷髅","italic": false,"color": "aqua"},"minecraft:lore":[{"translate":"丢出可以将其与自己绑定","italic": false,"color": "white"},{"translate":"召唤一个更加强大的骷髅","italic": false,"color": "red"},{"translate":"----------------------------","italic": false,"color": "gray"},{"translate":"生命值：","italic": false,"color": "gray"},{"translate":"持续时间：","italic": false,"color": "gray"},{"translate":"武器：","italic": false,"color": "gray"}],"entity_data": {"id": "skeleton","PersistenceRequired": true,"Health": 80,"CustomNameVisible": true,"CustomName": {"translate":"唤灵-精英骷髅"},"equipment": {"head": {"id":"diamond_helmet","count": 1,"components": {"enchantments": {"protection": 4}}},"chest": {"id":"diamond_chestplate","count": 1,"components": {"enchantments": {"protection": 4}}},"legs": {"id":"diamond_leggings","count": 1,"components": {"enchantments": {"protection": 4}}},"feet": {"id":"diamond_boots","count": 1,"components": {"enchantments": {"protection": 4}}},"mainhand": {"id":"bow","count": 1,"components": {"enchantments": {"power": 7,"punch": 2,"hunter": 3,"piercing": 1}}}},"CanPickUpLoot": true,"drop_chances": {"head": 0,"chest": 0,"legs": 0,"feet": 0,"mainhand": 0,"offhand": 0},"attributes": [{"id": "max_health","base": 80},{"id": "follow_range","base": 64},{"id": "movement_speed","base": 0.35}]},"custom_data": {"spawn_egg":1,"wallwar_item":1},"max_stack_size": 16}
            }
          ]
        }
        ]
    },{
      "bonus_rolls": 0.0,
      "rolls": 1.0,
      "entries": [
        {
          "type": "minecraft:item",
          "name": "minecraft:ender_pearl"
        }
        ]
    },{
      "bonus_rolls": 0.0,
      "rolls": 1.0,
      "entries": [
        {
          "type": "minecraft:item",
          "name": "minecraft:blaze_rod",
          "functions": [
            {
              "function": "minecraft:set_count",
              "count": 10
            }
          ]
        }
        ]
    },{
      "bonus_rolls": 0.0,
      "rolls": 1.0,
      "entries": [
        {
          "type": "minecraft:item",
          "name": "minecraft:nether_wart",
          "functions": [
            {
              "function": "minecraft:set_count",
              "count": 10
            }
          ]
        }
        ]
    },{
      "bonus_rolls": 0.0,
      "rolls": 1.0,
      "entries": [
        {
          "type": "minecraft:item",
          "functions": [
            {
              "add": false,
              "count": 6,
              "function": "minecraft:set_count"
            },
            {
              "function": "minecraft:set_potion",
              "id": "minecraft:strong_swiftness"
            }
          ],
          "name": "minecraft:splash_potion"
        }
        ]
    },{
      "bonus_rolls": 0.0,
      "rolls": 1.0,
      "entries": [
        {
          "type": "minecraft:item",
          "functions": [
            {
              "add": false,
              "count": 6,
              "function": "minecraft:set_count"
            },
            {
              "function": "minecraft:set_potion",
              "id": "minecraft:strong_strength"
            }
          ],
          "name": "minecraft:splash_potion"
        }
        ]
    }
  ]
}